{"height":16200,"speed":50,"screen":{"width":800,"height":900},"ennemies":[[{"type":"private","position":{"x":38,"y":-127},"pattern":[]},{"type":"private","position":{"x":68,"y":-152},"pattern":[]},{"type":"private","position":{"x":96,"y":-188},"pattern":[]},{"type":"private","position":{"x":119,"y":-219},"pattern":[]},{"type":"private","position":{"x":149,"y":-256},"pattern":[]},{"type":"private","position":{"x":173,"y":-287},"pattern":[]},{"type":"private","position":{"x":199,"y":-326},"pattern":[]},{"type":"private","position":{"x":232,"y":-372},"pattern":[]},{"type":"private","position":{"x":259,"y":-407},"pattern":[]},{"type":"private","position":{"x":286,"y":-445},"pattern":[]},{"type":"private","position":{"x":320,"y":-481},"pattern":[]},{"type":"private","position":{"x":348,"y":-504},"pattern":[]},{"type":"private","position":{"x":375,"y":-534},"pattern":[]},{"type":"private","position":{"x":401,"y":-566},"pattern":[]},{"type":"private","position":{"x":419,"y":-603},"pattern":[]},{"type":"private","position":{"x":441,"y":-562},"pattern":[]},{"type":"private","position":{"x":455,"y":-532},"pattern":[]},{"type":"private","position":{"x":485,"y":-486},"pattern":[]},{"type":"private","position":{"x":507,"y":-457},"pattern":[]},{"type":"private","position":{"x":538,"y":-415},"pattern":[]},{"type":"private","position":{"x":553,"y":-390},"pattern":[]},{"type":"private","position":{"x":573,"y":-338},"pattern":[]},{"type":"private","position":{"x":596,"y":-297},"pattern":[]},{"type":"private","position":{"x":611,"y":-280},"pattern":[]},{"type":"private","position":{"x":653,"y":-222},"pattern":[]},{"type":"private","position":{"x":680,"y":-204},"pattern":[]},{"type":"private","position":{"x":707,"y":-164},"pattern":[]},{"type":"private","position":{"x":745,"y":-145},"pattern":[]},{"type":"private","position":{"x":761,"y":-130},"pattern":[]}],[{"type":"sergeant","position":{"x":171,"y":-1543},"pattern":[]},{"type":"sergeant","position":{"x":298,"y":-1544},"pattern":[]},{"type":"sergeant","position":{"x":443,"y":-1546},"pattern":[]},{"type":"sergeant","position":{"x":591,"y":-1546},"pattern":[]},{"type":"private","position":{"x":40,"y":-1607},"pattern":[]},{"type":"private","position":{"x":139,"y":-1614},"pattern":[]},{"type":"private","position":{"x":233,"y":-1600},"pattern":[]},{"type":"private","position":{"x":329,"y":-1616},"pattern":[]},{"type":"private","position":{"x":429,"y":-1600},"pattern":[]},{"type":"private","position":{"x":524,"y":-1614},"pattern":[]},{"type":"private","position":{"x":633,"y":-1594},"pattern":[]},{"type":"private","position":{"x":727,"y":-1612},"pattern":[]},{"type":"private","position":{"x":24,"y":-926},"pattern":[]},{"type":"private","position":{"x":51,"y":-946},"pattern":[]},{"type":"private","position":{"x":88,"y":-965},"pattern":[]},{"type":"private","position":{"x":129,"y":-991},"pattern":[]},{"type":"private","position":{"x":221,"y":-1032},"pattern":[]},{"type":"private","position":{"x":267,"y":-1062},"pattern":[]},{"type":"private","position":{"x":338,"y":-1113},"pattern":[]},{"type":"private","position":{"x":398,"y":-1154},"pattern":[]},{"type":"private","position":{"x":492,"y":-1074},"pattern":[]},{"type":"private","position":{"x":566,"y":-1024},"pattern":[]},{"type":"private","position":{"x":713,"y":-938},"pattern":[]},{"type":"private","position":{"x":747,"y":-924},"pattern":[]},{"type":"private","position":{"x":631,"y":-978},"pattern":[]}],[{"type":"major","position":{"x":409,"y":-2592},"pattern":[]},{"type":"major","position":{"x":651,"y":-2419},"pattern":[]},{"type":"major","position":{"x":167,"y":-2423},"pattern":[]},{"type":"private","position":{"x":411,"y":-2453},"pattern":[]}],[],[]]}